SAPOFTO/SAPOFTO.py
SAPOFTO/__init__.py
SAPOFTO-0.0.15.dist-info/LICENSE
SAPOFTO-0.0.15.dist-info/METADATA
SAPOFTO-0.0.15.dist-info/WHEEL
SAPOFTO-0.0.15.dist-info/top_level.txt
SAPOFTO-0.0.15.dist-info/RECORD
