Metadata-Version: 2.1
Name: SAPOFTO
Version: 0.0.15
Summary: Parse, compose, evaluate and execute org files and data in org-down notation.
Home-page: https://github.com/shaneallcroft/SAPOFTO
Author: Shane Allcroft
Author-email: shaneallcroft@fedoraproject.org
License: UNKNOWN
Project-URL: Bug Tracker, https://github.com/shaneallcroft/SAPOFTO/issues
Platform: UNKNOWN
Classifier: Programming Language :: Python :: 3
Classifier: License :: OSI Approved :: MIT License
Classifier: Operating System :: OS Independent
Requires-Python: >=3.6
License-File: LICENSE
